LICENSE
README.md
setup.py
KeyConfig/__init__.py
KeyConfig.egg-info/PKG-INFO
KeyConfig.egg-info/SOURCES.txt
KeyConfig.egg-info/dependency_links.txt
KeyConfig.egg-info/top_level.txt